cpp/mgcg_cuda/CMakeLists.txt
cpp/mgcg_cuda/fastmg.cu
cpp/mgcg_cuda/kernels.cuh
cpp/mgcg_cuda/README.md
engine/cloth/__init__.py
engine/cloth/cloth3d.py
engine/soft/soft3d.py
tipbd-0.1.2.dist-info/METADATA
tipbd-0.1.2.dist-info/WHEEL
tipbd-0.1.2.dist-info/RECORD
