Metadata-Version: 2.1
Name: tipbd
Version: 0.1.2
Summary: Multigrid PBD engine
Author: Chunlei Li
Requires-Python: >=3.9,<4.0
Classifier: Programming Language :: Python :: 3
Classifier: Programming Language :: Python :: 3.9
Classifier: Programming Language :: Python :: 3.10
Classifier: Programming Language :: Python :: 3.11
Classifier: Programming Language :: Python :: 3.12
Project-URL: repository, https://github.com/chunleili/tiPBD/tree/amg
